etc/gradient_one.cfg.sample
gradientone/__init__.py
gradientone/always_on.py
gradientone/base.py
gradientone/command_runners.py
gradientone/controllers.py
gradientone/gateway_client.py
gradientone/gateway_helpers.py
gradientone/hang5.py
gradientone/ivi_instruments.py
gradientone/master.py
gradientone/sample_utilization.py
gradientone/scope.py
gradientone/send_script_client.py
gradientone/send_script_post.py
gradientone/settings.py
gradientone/tek_gateway.py
gradientone/tek_grl_qw.py
gradientone/test_vxi11_discovery.py
gradientone/transmitters.py
gradientone/ts.py
gradientone/utilization.py
gradientone/version.py
gradientone/data_manipulation/GCE_client.py
gradientone/data_manipulation/__init__.py
gradientone/data_manipulation/grl.py
gradientone/data_manipulation/helper_functions.py
gradientone/data_manipulation/matlab_conversion.py
gradientone/data_manipulation/touchstone.py
gradientone/device_drivers/__init__.py
gradientone/device_drivers/agilent.py
gradientone/device_drivers/base_driver.py
gradientone/device_drivers/bscopetestapi.py
gradientone/device_drivers/device_drivers_parent_path.py
gradientone/device_drivers/dummy_scope.py
gradientone/device_drivers/grl_test_driver.py
gradientone/device_drivers/scope_driver.py
gradientone/device_drivers/test.py
gradientone/device_drivers/usb_controller.py
gradientone/device_drivers/xtend.py
gradientone/device_drivers/can/CANcard.py
gradientone/device_drivers/can/__init__.py
gradientone/device_drivers/can/can_headers.py
gradientone/device_drivers/can/can_helpers.py
gradientone/device_drivers/can/motor.py
gradientone/device_drivers/keysight/__init__.py
gradientone/device_drivers/keysight/keysightMSO9064A.py
gradientone/device_drivers/keysight/keysightMSO9104A.py
gradientone/device_drivers/keysight/keysight_parent_path.py
gradientone/device_drivers/keysight/keysight_scope.py
gradientone/device_drivers/rigol/__init__.py
gradientone/device_drivers/rigol/rigolDS1000Z.py
gradientone-1.0.0.dist-info/METADATA
gradientone-1.0.0.dist-info/RECORD
gradientone-1.0.0.dist-info/WHEEL
gradientone-1.0.0.dist-info/dependency_links.txt
gradientone-1.0.0.dist-info/entry_points.txt
gradientone-1.0.0.dist-info/top_level.txt
