Metadata-Version: 2.1
Name: gradientone
Version: 1.0.0
Summary: Gateway client for GradientOne
Home-page: http://www.gradientone.com
Author: GradientOne Team
Author-email: dev@gradientone.com
License: MIT
Keywords: test and measurement device control and data collection
Platform: UNKNOWN
Classifier: Development Status :: 3 - Alpha
Classifier: Intended Audience :: Developers
Classifier: Topic :: Software Development :: Build Tools
Classifier: License :: OSI Approved :: MIT License
Classifier: Programming Language :: Python :: 2
Classifier: Programming Language :: Python :: 2.7
Classifier: Programming Language :: Python :: 3
Classifier: Programming Language :: Python :: 3.3
Classifier: Programming Language :: Python :: 3.4
Classifier: Programming Language :: Python :: 3.5
Requires-Dist: enum34
Requires-Dist: numpy
Requires-Dist: grequests
Requires-Dist: oauth2client
Requires-Dist: jsonpickle
Requires-Dist: psutil
Requires-Dist: pyusb
Requires-Dist: requests-toolbelt
Requires-Dist: raven
Requires-Dist: ifparser
